Metadata-Version: 2.1
Name: apolo-flow
Version: 24.12.1
Summary: Pipelines system for Apolo MLOps platform
Home-page: https://github.com/neuro-inc/neuro-flow
Author: Apolo Team
Author-email: dev@apolo.us
License: Apache 2
Classifier: Programming Language :: Python :: 3
Classifier: Programming Language :: Python :: 3.9
Classifier: Programming Language :: Python :: 3.10
Classifier: Programming Language :: Python :: 3.11
Classifier: Programming Language :: Python :: 3.12
Classifier: Operating System :: OS Independent
Classifier: Development Status :: 4 - Beta
Classifier: Environment :: Console
Classifier: Intended Audience :: Developers
Classifier: Intended Audience :: Science/Research
Classifier: Intended Audience :: Information Technology
Classifier: Topic :: Scientific/Engineering :: Artificial Intelligence
Classifier: Topic :: Software Development
Classifier: Topic :: Utilities
Classifier: License :: OSI Approved :: Apache Software License
Requires-Python: >=3.9.0
License-File: LICENSE
Requires-Dist: apolo-cli>=24.12.1
Requires-Dist: pyyaml>=5.4
Requires-Dist: funcparserlib>=1.0.0
Requires-Dist: humanize>=4.10
Requires-Dist: apolo-extras>=24.10.0
Requires-Dist: graphviz>=0.20.3
Requires-Dist: yarl>=1.13
Requires-Dist: multidict<7.0,>=5.0
Requires-Dist: rich>=13.7.0
Requires-Dist: typing-extensions>=3.10
Requires-Dist: click>=8.0
